dbetto/__init__.py
dbetto/_version.py
dbetto/_version.pyi
dbetto/attrsdict.py
dbetto/catalog.py
dbetto/py.typed
dbetto/textdb.py
dbetto/time.py
dbetto/utils.py
dbetto-1.2.4.dist-info/METADATA
dbetto-1.2.4.dist-info/WHEEL
dbetto-1.2.4.dist-info/licenses/LICENSE
dbetto-1.2.4.dist-info/RECORD
